bookfolder/__init__.py
bookfolder/formatter.py
bookfolder/pattern_creator.py
bookfolder/pdf.py
bookfolder/sheet.py
bookfolder/gui/__init__.py
bookfolder/gui/gui.py
bookfolder/gui/widgets.py
bookfolder/scripts/__init__.py
bookfolder/scripts/cli.py
bookfolder/scripts/gui.py
bookfolder-0.5.dist-info/LICENSE.md
bookfolder-0.5.dist-info/METADATA
bookfolder-0.5.dist-info/WHEEL
bookfolder-0.5.dist-info/entry_points.txt
bookfolder-0.5.dist-info/top_level.txt
bookfolder-0.5.dist-info/RECORD
