Metadata-Version: 2.1
Name: bookfolder
Version: 0.5
Summary: Convert an image into a bookfolding pattern
Home-page: https://github.com/aajarven/bookfolder
Author: Anni Järvenpää
License: UNKNOWN
Platform: UNKNOWN
Requires-Python: >=3.6
License-File: LICENSE.md
Requires-Dist: click
Requires-Dist: imageio
Requires-Dist: fpdf2
